dicomthings/__init__.py
dicomthings/dicom.py
dicomthings-0.11.1.dist-info/licenses/LICENSE
dicomthings-0.11.1.dist-info/METADATA
dicomthings-0.11.1.dist-info/WHEEL
dicomthings-0.11.1.dist-info/top_level.txt
dicomthings-0.11.1.dist-info/RECORD
