Metadata-Version: 2.4
Name: dicomthings
Version: 0.11.1
Summary: A Python library for working with DICOM files.
Author-email: Jeroen Bertels <jeroen.bertels@gmail.com>
Project-URL: Homepage, https://github.com/JeroenBertels/dicomthings
Classifier: Programming Language :: Python :: 3
Classifier: License :: OSI Approved :: Apache Software License
Classifier: Operating System :: OS Independent
Requires-Python: >=3.8
License-File: LICENSE
Requires-Dist: numpy
Requires-Dist: nibabel
Requires-Dist: pydicom
Requires-Dist: dicom2nifti
Requires-Dist: niftithings
Requires-Dist: iothings
Dynamic: license-file
